parkr/__init__.py
parkr/__main__.py
parkr/activation.py
parkr/network.py
parkr/tests/__init__.py
parkr/tests/back_prop_test.py
parkr-1.0.2.dist-info/LICENSE.md
parkr-1.0.2.dist-info/METADATA
parkr-1.0.2.dist-info/WHEEL
parkr-1.0.2.dist-info/top_level.txt
parkr-1.0.2.dist-info/RECORD
