Metadata-Version: 2.1
Name: parkr
Version: 1.0.2
Summary: A lightweight basic neural networks library in Python
Home-page: https://github.com/OlliePugh/parkr
Author: Ollie Pugh
Author-email: oliver.pugh@mac.com
License: UNKNOWN
Project-URL: Bug Tracker, https://github.com/OlliePugh/parkr/issues
Platform: UNKNOWN
Classifier: Programming Language :: Python :: 3
Classifier: License :: OSI Approved :: MIT License
Classifier: Operating System :: OS Independent
Requires-Python: >=3.6
License-File: LICENSE.md
Requires-Dist: numpy
